beautiful_traceback/__init__.py
beautiful_traceback/_extension.py
beautiful_traceback/cli.py
beautiful_traceback/common.py
beautiful_traceback/formatting.py
beautiful_traceback/hook.py
beautiful_traceback/parsing.py
beautiful_traceback/pytest_plugin.py
beautiful_traceback-0.2.0.dist-info/WHEEL
beautiful_traceback-0.2.0.dist-info/entry_points.txt
beautiful_traceback-0.2.0.dist-info/METADATA
beautiful_traceback-0.2.0.dist-info/RECORD
