Metadata-Version: 2.3
Name: beautiful-traceback
Version: 0.2.0
Summary: Beautiful, readable Python tracebacks with colors and formatting
Keywords: traceback,error,debugging,formatting
Author: Michael Bianco
Author-email: Michael Bianco <mike@mikebian.co>
Requires-Dist: colorama>=0.4.6
Requires-Python: >=3.9
Project-URL: Repository, https://github.com/iloveitaly/beautiful-traceback
